{
  ".": "23.6.0",
  "packages/api-explorer": "0.9.46",
  "packages/code-editor": "0.1.28",
  "packages/extension-api-explorer": "22.21.3",
  "packages/extension-sdk": "23.6.0",
  "packages/extension-sdk-react": "23.6.0",
  "packages/extension-utils": "0.1.23",
  "packages/hackathon": "22.21.5",
  "packages/run-it": "0.9.46",
  "packages/sdk": "23.6.0",
  "packages/sdk-codegen": "21.8.0",
  "packages/sdk-codegen-scripts": "21.5.3",
  "packages/sdk-codegen-utils": "21.0.11",
  "packages/sdk-node": "23.6.0",
  "packages/sdk-rtl": "21.6.0",
  "packages/wholly-artifact": "0.1.4",
  "packages/wholly-sheet": "0.5.42",
  "python": "23.6.0",
  "packages/extension-playground": "1.0.3"
}
