{
  ".": "1.17.0",
  "packages/api-explorer": "0.9.21",
  "packages/code-editor": "0.1.12",
  "packages/extension-api-explorer": "21.18.0",
  "packages/extension-sdk": "21.18.0",
  "packages/extension-sdk-react": "21.18.0",
  "packages/hackathon": "21.18.0",
  "packages/run-it": "0.9.21",
  "packages/sdk": "21.18.0",
  "packages/sdk-codegen": "21.1.0",
  "packages/sdk-codegen-scripts": "21.1.1",
  "packages/sdk-codegen-utils": "21.0.11",
  "packages/sdk-node": "21.18.0",
  "packages/sdk-rtl": "21.1.0",
  "packages/wholly-sheet": "0.5.18",
  "python": "21.18.0"
}
